README.rst
setup.cfg
setup.py
datapipelines/__init__.py
datapipelines/common.py
datapipelines/pipelines.py
datapipelines/sinks.py
datapipelines/sources.py
datapipelines/transformers.py
datapipelines.egg-info/PKG-INFO
datapipelines.egg-info/SOURCES.txt
datapipelines.egg-info/dependency_links.txt
datapipelines.egg-info/requires.txt
datapipelines.egg-info/top_level.txt
datapipelines.egg-info/zip-safe
tests/__init__.py
tests/test_pipelines.py
tests/test_sinks.py
tests/test_sources.py
tests/test_transformers.py