Metadata-Version: 1.1
Name: datapipelines
Version: 0.0.1.dev2
Summary: Caching abstraction layer for orchestrating multiple cache tiers
Home-page: https://github.com/meraki-analytics/datapipelines
Author: Rob Rua
Author-email: robrua@alumni.cmu.edu
License: MIT
Platform: UNKNOWN
Classifier: Development Status :: 4 - Beta
Classifier: Intended Audience :: Developers
Classifier: License :: OSI Approved :: MIT License
Classifier: Operating System :: OS Independent
Classifier: Programming Language :: Python
Classifier: Programming Language :: Python :: 3
Classifier: Programming Language :: Python :: 3 :: Only
Classifier: Topic :: Database :: Front-Ends
